rapidsmpf/GIT_COMMIT
rapidsmpf/VERSION
rapidsmpf/__init__.pxd
rapidsmpf/__init__.py
rapidsmpf/_version.py
rapidsmpf/config.cpython-313-aarch64-linux-gnu.so
rapidsmpf/config.pxd
rapidsmpf/config.pyi
rapidsmpf/cuda_stream.cpython-313-aarch64-linux-gnu.so
rapidsmpf/cuda_stream.pxd
rapidsmpf/cuda_stream.pyi
rapidsmpf/cupti.pxd
rapidsmpf/cupti.pyi
rapidsmpf/owning_wrapper.pxd
rapidsmpf/progress_thread.cpython-313-aarch64-linux-gnu.so
rapidsmpf/progress_thread.pxd
rapidsmpf/progress_thread.pyi
rapidsmpf/rmm_resource_adaptor.cpython-313-aarch64-linux-gnu.so
rapidsmpf/rmm_resource_adaptor.pxd
rapidsmpf/rmm_resource_adaptor.pyi
rapidsmpf/shuffler.cpython-313-aarch64-linux-gnu.so
rapidsmpf/shuffler.pxd
rapidsmpf/shuffler.pyi
rapidsmpf/statistics.cpython-313-aarch64-linux-gnu.so
rapidsmpf/statistics.pxd
rapidsmpf/statistics.pyi
rapidsmpf/testing.py
rapidsmpf/_detail/__init__.pxd
rapidsmpf/_detail/__init__.py
rapidsmpf/_detail/config_options_get.cpython-313-aarch64-linux-gnu.so
rapidsmpf/_detail/config_options_get.pxd
rapidsmpf/_detail/exception_handling.cpython-313-aarch64-linux-gnu.so
rapidsmpf/_detail/exception_handling.pxd
rapidsmpf/allgather/__init__.pxd
rapidsmpf/allgather/__init__.py
rapidsmpf/allgather/allgather.cpython-313-aarch64-linux-gnu.so
rapidsmpf/allgather/allgather.pxd
rapidsmpf/allgather/allgather.pyi
rapidsmpf/benchmarks/__init__.py
rapidsmpf/benchmarks/streaming_benchmark.py
rapidsmpf/buffer/__init__.pxd
rapidsmpf/buffer/__init__.py
rapidsmpf/buffer/buffer.cpython-313-aarch64-linux-gnu.so
rapidsmpf/buffer/buffer.pxd
rapidsmpf/buffer/buffer.pyi
rapidsmpf/buffer/content_description.cpython-313-aarch64-linux-gnu.so
rapidsmpf/buffer/content_description.pxd
rapidsmpf/buffer/content_description.pyi
rapidsmpf/buffer/packed_data.cpython-313-aarch64-linux-gnu.so
rapidsmpf/buffer/packed_data.pxd
rapidsmpf/buffer/packed_data.pyi
rapidsmpf/buffer/resource.cpython-313-aarch64-linux-gnu.so
rapidsmpf/buffer/resource.pxd
rapidsmpf_cu13-25.12.0.dist-info/METADATA
rapidsmpf_cu13-25.12.0.dist-info/WHEEL
rapidsmpf_cu13-25.12.0.dist-info/RECORD
rapidsmpf_cu13-25.12.0.dist-info/licenses/LICENSE
